README.md
setup.py
scheming/__init__.py
scheming/exceptions.py
scheming/models.py
scheming.egg-info/PKG-INFO
scheming.egg-info/SOURCES.txt
scheming.egg-info/dependency_links.txt
scheming.egg-info/top_level.txt
scheming/backends/__init__.py
scheming/backends/base.py
scheming/backends/mysql.py
scheming/backends/postgresql.py
scheming/backends/redshift.py