Metadata-Version: 2.1
Name: scheming
Version: 0.0.1
Summary: Schema discovery tool
Home-page: https://github.com/scruwys/scheming
Author: Scott Cruwys
Author-email: scruwys@gmail.com
License: UNKNOWN
Platform: UNKNOWN
Classifier: Programming Language :: Python :: 3
Classifier: License :: OSI Approved :: MIT License
Classifier: Operating System :: OS Independent
